{
  "version": "1.0",
  "last_updated": "2026-02-20T00:00:00Z",
  "libraries": {
    "supabase": {
      "files": [
        {
          "filename": "jwks-jwt-verification-fastapi-python.md",
          "topic": "JWKS verification in Python/FastAPI",
          "tech_stack": "Supabase + FastAPI + PyJWT",
          "fetched": "2026-02-20T00:00:00Z",
          "source": "Context7 API + official docs"
        },
        {
          "filename": "token-error-handling-secure-logging.md",
          "topic": "Auth error handling and secure logging",
          "tech_stack": "FastAPI + OWASP",
          "fetched": "2026-02-20T00:00:00Z",
          "source": "Official docs"
        }
      ]
    }
  }
}
