[
  {
    "source": "timeline.pdf",
    "chunk_id": "timeline-1",
    "content": "Project Alpha timeline targets Q2 launch and depends on Data Platform Upgrade completion."
  },
  {
    "source": "timeline.pdf",
    "chunk_id": "timeline-2",
    "content": "Integration testing is planned after Security Review and before release readiness sign-off."
  },
  {
    "source": "owner_notes.md",
    "chunk_id": "owner-1",
    "content": "Engineering owns dependency mapping while Product owns delivery milestones and change control."
  }
]
